sqlalchemy_crud_plus/__init__.py
sqlalchemy_crud_plus/crud.py
sqlalchemy_crud_plus/errors.py
sqlalchemy_crud_plus/py.typed
sqlalchemy_crud_plus/types.py
sqlalchemy_crud_plus/utils.py
sqlalchemy_crud_plus-1.13.1.dist-info/METADATA
sqlalchemy_crud_plus-1.13.1.dist-info/WHEEL
sqlalchemy_crud_plus-1.13.1.dist-info/licenses/LICENSE
sqlalchemy_crud_plus-1.13.1.dist-info/RECORD
