Metadata-Version: 2.4
Name: sqlalchemy-crud-plus
Version: 1.13.1
Summary: Advanced asynchronous CRUD SDK built on SQLAlchemy 2.0
Project-URL: homepage, https://github.com/fastapi-practices/sqlalchemy-crud-plus
Project-URL: repository, https://github.com/fastapi-practices/sqlalchemy-crud-plus
Author-email: Wu Clan <jianhengwu0407@gmail.com>
License: MIT
License-File: LICENSE
Classifier: License :: OSI Approved :: MIT License
Classifier: Programming Language :: Python :: 3 :: Only
Classifier: Programming Language :: Python :: 3.10
Classifier: Programming Language :: Python :: 3.11
Classifier: Programming Language :: Python :: 3.12
Classifier: Programming Language :: Python :: 3.13
Classifier: Programming Language :: Python :: 3.14
Requires-Python: >=3.10
Requires-Dist: pydantic>=2.0
Requires-Dist: sqlalchemy>=2.0.0
